pdftoimg/__init__.py
pdftoimg/pdftoimg.py
pdftoimg-0.1.1.dist-info/LICENSE
pdftoimg-0.1.1.dist-info/METADATA
pdftoimg-0.1.1.dist-info/WHEEL
pdftoimg-0.1.1.dist-info/entry_points.txt
pdftoimg-0.1.1.dist-info/top_level.txt
pdftoimg-0.1.1.dist-info/RECORD
