Metadata-Version: 2.1
Name: pdftoimg
Version: 0.1.1
Summary: Easily convert PDF to Image from command line
Home-page: https://github.com/starkblaze01/Pdf-To-Image
Author: starkblaze01
Author-email: mp.pathela@gmail.com
License: MIT
Keywords: pdf-to-image convert
Platform: UNKNOWN
Classifier: Development Status :: 5 - Production/Stable
Classifier: Programming Language :: Python :: 3
Classifier: Programming Language :: Python :: 3.5
Classifier: Programming Language :: Python :: 3.6
Classifier: Programming Language :: Python :: 3.7
Classifier: Programming Language :: Python :: 3.8
Classifier: License :: OSI Approved :: MIT License
Classifier: Operating System :: Unix
Requires-Python: >=3.6
Requires-Dist: pdf2image (>=1.11.0)
